Metadata-Version: 2.1
Name: BIGCrawler
Version: 1.0.0
Summary: Crawler program for BIG database
Home-page: https://github.com/yueyue970506/BIGCrawler
Author: Yuechen Qi
Author-email: 519584766@qq.com
License: MIT
Platform: UNKNOWN
